{"idx_to_token": {"1": "c", "2": "a", "3": "u", "4": "s", "5": "e", "6": "d", "7": " ", "8": "i", "9": "n", "10": "t", "11": "h", "12": "b", "13": "l", "14": "w", "15": "o", "16": "\n", "17": "f", "18": "m", "19": "p", "20": "'", "21": ",", "22": "r", "23": "v", "24": ".", "25": "B", "26": "g", "27": "q", "28": "H", "29": "k", "30": "S", "31": "y", "32": "-", "33": "M", "34": "P", "35": "K", "36": "W", "37": "F", "38": "V", "39": "j", "40": "3", "41": "2", "42": "8", "43": "L", "44": "!", "45": "\"", "46": "6", "47": "9", "48": "A", "49": "C", "50": "J", "51": "T", "52": "O", "53": "?", "54": "E", "55": "=", "56": ";", "57": "R", "58": "I", "59": "D", "60": "z", "61": "5", "62": "1", "63": "]", "64": ":", "65": "N", "66": "4", "67": ")", "68": "G", "69": "_", "70": "x", "71": "(", "72": "7", "73": "0", "74": "Y", "75": "[", "76": "#", "77": "\t"}, "token_to_idx": {"\t": 77, "\n": 16, "!": 44, " ": 7, "#": 76, "\"": 45, "'": 20, ")": 67, "(": 71, "-": 32, ",": 21, ".": 24, "1": 62, "0": 73, "3": 40, "2": 41, "5": 61, "4": 66, "7": 72, "6": 46, "9": 47, "8": 42, ";": 56, ":": 64, "=": 55, "?": 53, "A": 48, "C": 49, "B": 25, "E": 54, "D": 59, "G": 68, "F": 37, "I": 58, "H": 28, "K": 35, "J": 50, "M": 33, "L": 43, "O": 52, "N": 65, "P": 34, "S": 30, "R": 57, "T": 51, "W": 36, "V": 38, "Y": 74, "[": 75, "]": 63, "_": 69, "a": 2, "c": 1, "b": 12, "e": 5, "d": 6, "g": 26, "f": 17, "i": 8, "h": 11, "k": 29, "j": 39, "m": 18, "l": 13, "o": 15, "n": 9, "q": 27, "p": 19, "s": 4, "r": 22, "u": 3, "t": 10, "w": 14, "v": 23, "y": 31, "x": 70, "z": 60}}