{"idx_to_token": {"1": "e", "2": " ", "3": "a", "4": "d", "5": "j", "6": "u", "7": "t", "8": "n", "9": "A", "10": "m", "11": "r", "12": "i", "13": "c", "14": "o", "15": "s", "16": ".", "17": "\n", "18": "\"", "19": ",", "20": "I", "21": "g", "22": "v", "23": "l", "24": "M", "25": "'", "26": "w", "27": "k", "28": "y", "29": "h", "30": "f", "31": "H", "32": "-", "33": "p", "34": "G", "35": "U", "36": "S", "37": "x", "38": "T", "39": "b", "40": "5", "41": "C", "42": "W", "43": "1", "44": "7", "45": "P", "46": "O", "47": "!", "48": "_", "49": "6", "50": "2", "51": "4", "52": "0", "53": "3", "54": "z", "55": ";", "56": "Y", "57": ":", "58": "?", "59": "V", "60": "9", "61": "L", "62": "B", "63": "D", "64": "#", "65": "q", "66": "N", "67": "8", "68": "R", "69": "J", "70": "K", "71": ")", "72": "F", "73": "E", "74": "$", "75": "=", "76": "(", "77": "*", "78": "]", "79": "\t"}, "token_to_idx": {"\t": 79, "\n": 17, "!": 47, " ": 2, "#": 64, "\"": 18, "$": 74, "'": 25, ")": 71, "(": 76, "*": 77, "-": 32, ",": 19, ".": 16, "1": 43, "0": 52, "3": 53, "2": 50, "5": 40, "4": 51, "7": 44, "6": 49, "9": 60, "8": 67, ";": 55, ":": 57, "=": 75, "?": 58, "A": 9, "C": 41, "B": 62, "E": 73, "D": 63, "G": 34, "F": 72, "I": 20, "H": 31, "K": 70, "J": 69, "M": 24, "L": 61, "O": 46, "N": 66, "P": 45, "S": 36, "R": 68, "U": 35, "T": 38, "W": 42, "V": 59, "Y": 56, "]": 78, "_": 48, "a": 3, "c": 13, "b": 39, "e": 1, "d": 4, "g": 21, "f": 30, "i": 12, "h": 29, "k": 27, "j": 5, "m": 10, "l": 23, "o": 14, "n": 8, "q": 65, "p": 33, "s": 15, "r": 11, "u": 6, "t": 7, "w": 26, "v": 22, "y": 28, "x": 37, "z": 54}}