{"idx_to_token": {"1": "o", "2": "n", "3": "d", "4": " ", "5": "l", "6": "i", "7": "k", "8": "e", "9": ",", "10": "s", "11": "m", "12": "t", "13": "h", "14": "g", "15": "f", "16": "r", "17": "a", "18": "y", "19": "w", "20": "b", "21": "v", "22": "c", "23": "p", "24": "!", "25": "I", "26": ".", "27": "\n", "28": "5", "29": "1", "30": "0", "31": "S", "32": "\"", "33": "D", "34": "W", "35": "V", "36": "J", "37": "u", "38": "T", "39": ":", "40": "O", "41": "4", "42": "9", "43": "2", "44": "P", "45": "A", "46": "6", "47": "C", "48": "B", "49": "'", "50": "R", "51": "-", "52": "j", "53": "H", "54": "F", "55": "M", "56": ";", "57": "=", "58": "x", "59": "L", "60": "q", "61": "Y", "62": "3", "63": "7", "64": "N", "65": "K", "66": "X", "67": "_", "68": "8", "69": "E", "70": "?", "71": "G", "72": "(", "73": "#", "74": ")", "75": "U", "76": "[", "77": "z", "78": "\t"}, "token_to_idx": {"\t": 78, "\n": 27, "!": 24, " ": 4, "#": 73, "\"": 32, "'": 49, ")": 74, "(": 72, "-": 51, ",": 9, ".": 26, "1": 29, "0": 30, "3": 62, "2": 43, "5": 28, "4": 41, "7": 63, "6": 46, "9": 42, "8": 68, ";": 56, ":": 39, "=": 57, "?": 70, "A": 45, "C": 47, "B": 48, "E": 69, "D": 33, "G": 71, "F": 54, "I": 25, "H": 53, "K": 65, "J": 36, "M": 55, "L": 59, "O": 40, "N": 64, "P": 44, "S": 31, "R": 50, "U": 75, "T": 38, "W": 34, "V": 35, "Y": 61, "X": 66, "[": 76, "_": 67, "a": 17, "c": 22, "b": 20, "e": 8, "d": 3, "g": 14, "f": 15, "i": 6, "h": 13, "k": 7, "j": 52, "m": 11, "l": 5, "o": 1, "n": 2, "q": 60, "p": 23, "s": 10, "r": 16, "u": 37, "t": 12, "w": 19, "v": 21, "y": 18, "x": 58, "z": 77}}