{"idx_to_token": {"1": "i", "2": "s", "3": " ", "4": "l", "5": "e", "6": "t", "7": "r", "8": ".", "9": "\n", "10": "A", "11": "h", "12": "a", "13": "m", "14": "o", "15": "c", "16": "d", "17": "f", "18": "g", "19": "n", "20": "u", "21": "b", "22": ",", "23": "x", "24": "p", "25": "v", "26": "w", "27": "T", "28": "y", "29": "P", "30": "D", "31": "j", "32": "k", "33": "I", "34": "q", "35": "B", "36": ";", "37": "H", "38": "N", "39": "_", "40": "!", "41": "\"", "42": "S", "43": "W", "44": "?", "45": "M", "46": "Y", "47": "'", "48": "G", "49": "R", "50": "=", "51": "-", "52": "F", "53": "1", "54": "7", "55": "5", "56": "8", "57": "C", "58": "#", "59": "4", "60": "9", "61": ":", "62": "O", "63": "V", "64": "(", "65": "0", "66": "E", "67": "3", "68": "U", "69": "L", "70": "K", "71": "J", "72": "Q", "73": "]", "74": "z", "75": ")", "76": "$", "77": "2", "78": "X", "79": "[", "80": "6", "81": "\t"}, "token_to_idx": {"\t": 81, "\n": 9, "!": 40, " ": 3, "#": 58, "\"": 41, "$": 76, "'": 47, ")": 75, "(": 64, "-": 51, ",": 22, ".": 8, "1": 53, "0": 65, "3": 67, "2": 77, "5": 55, "4": 59, "7": 54, "6": 80, "9": 60, "8": 56, ";": 36, ":": 61, "=": 50, "?": 44, "A": 10, "C": 57, "B": 35, "E": 66, "D": 30, "G": 48, "F": 52, "I": 33, "H": 37, "K": 70, "J": 71, "M": 45, "L": 69, "O": 62, "N": 38, "Q": 72, "P": 29, "S": 42, "R": 49, "U": 68, "T": 27, "W": 43, "V": 63, "Y": 46, "X": 78, "[": 79, "]": 73, "_": 39, "a": 12, "c": 15, "b": 21, "e": 5, "d": 16, "g": 18, "f": 17, "i": 1, "h": 11, "k": 32, "j": 31, "m": 13, "l": 4, "o": 14, "n": 19, "q": 34, "p": 24, "s": 2, "r": 7, "u": 20, "t": 6, "w": 26, "v": 25, "y": 28, "x": 23, "z": 74}}