{"idx_to_token": {"1": " ", "2": "e", "3": "l", "4": "c", "5": "i", "6": "s", "7": "m", "8": "t", "9": "w", "10": "h", "11": "W", "12": "n", "13": "g", "14": ".", "15": "\n", "16": "\"", "17": "N", "18": "o", "19": ",", "20": "a", "21": "x", "22": "_", "23": "O", "24": "I", "25": "b", "26": "!", "27": "Y", "28": "u", "29": "r", "30": "d", "31": "f", "32": "p", "33": "v", "34": "G", "35": "A", "36": "y", "37": "-", "38": "S", "39": "k", "40": "E", "41": "T", "42": "D", "43": "j", "44": "1", "45": "8", "46": "9", "47": "'", "48": "?", "49": "P", "50": "4", "51": "3", "52": "7", "53": "6", "54": "C", "55": "V", "56": "J", "57": "B", "58": "L", "59": "R", "60": ":", "61": "H", "62": "M", "63": "=", "64": ")", "65": "U", "66": ";", "67": "0", "68": "5", "69": "2", "70": "F", "71": "(", "72": "]", "73": "z", "74": "X", "75": "#", "76": "q", "77": "K", "78": "$", "79": "\t"}, "token_to_idx": {"\t": 79, "\n": 15, "!": 26, " ": 1, "#": 75, "\"": 16, "$": 78, "'": 47, ")": 64, "(": 71, "-": 37, ",": 19, ".": 14, "1": 44, "0": 67, "3": 51, "2": 69, "5": 68, "4": 50, "7": 52, "6": 53, "9": 46, "8": 45, ";": 66, ":": 60, "=": 63, "?": 48, "A": 35, "C": 54, "B": 57, "E": 40, "D": 42, "G": 34, "F": 70, "I": 24, "H": 61, "K": 77, "J": 56, "M": 62, "L": 58, "O": 23, "N": 17, "P": 49, "S": 38, "R": 59, "U": 65, "T": 41, "W": 11, "V": 55, "Y": 27, "X": 74, "]": 72, "_": 22, "a": 20, "c": 4, "b": 25, "e": 2, "d": 30, "g": 13, "f": 31, "i": 5, "h": 10, "k": 39, "j": 43, "m": 7, "l": 3, "o": 18, "n": 12, "q": 76, "p": 32, "s": 6, "r": 29, "u": 28, "t": 8, "w": 9, "v": 33, "y": 36, "x": 21, "z": 73}}