{"idx_to_token": {"1": "r", "2": "u", "3": "l", "4": "e", "5": " ", "6": "i", "7": "n", "8": "t", "9": "h", "10": "\n", "11": "s", "12": "f", "13": "c", "14": "y", "15": "a", "16": "d", "17": "b", "18": "o", "19": "k", "20": "p", "21": "m", "22": "U", "23": "S", "24": ";", "25": "g", "26": "P", "27": ",", "28": "w", "29": "B", "30": "G", "31": ".", "32": "\"", "33": "O", "34": "'", "35": "!", "36": "W", "37": "I", "38": "A", "39": "F", "40": "_", "41": "Y", "42": "N", "43": "v", "44": "=", "45": "D", "46": "j", "47": "T", "48": "C", "49": "x", "50": "6", "51": "J", "52": "8", "53": "5", "54": "?", "55": "E", "56": "H", "57": "3", "58": "-", "59": "2", "60": "V", "61": "$", "62": ")", "63": "M", "64": "L", "65": "R", "66": "K", "67": "4", "68": "0", "69": "1", "70": ":", "71": "*", "72": "q", "73": "z", "74": "#", "75": "7", "76": "9", "77": "X", "78": "(", "79": "/", "80": "\t"}, "token_to_idx": {"\t": 80, "\n": 10, "!": 35, " ": 5, "#": 74, "\"": 32, "$": 61, "'": 34, ")": 62, "(": 78, "*": 71, "-": 58, ",": 27, "/": 79, ".": 31, "1": 69, "0": 68, "3": 57, "2": 59, "5": 53, "4": 67, "7": 75, "6": 50, "9": 76, "8": 52, ";": 24, ":": 70, "=": 44, "?": 54, "A": 38, "C": 48, "B": 29, "E": 55, "D": 45, "G": 30, "F": 39, "I": 37, "H": 56, "K": 66, "J": 51, "M": 63, "L": 64, "O": 33, "N": 42, "P": 26, "S": 23, "R": 65, "U": 22, "T": 47, "W": 36, "V": 60, "Y": 41, "X": 77, "_": 40, "a": 15, "c": 13, "b": 17, "e": 4, "d": 16, "g": 25, "f": 12, "i": 6, "h": 9, "k": 19, "j": 46, "m": 21, "l": 3, "o": 18, "n": 7, "q": 72, "p": 20, "s": 11, "r": 1, "u": 2, "t": 8, "w": 28, "v": 43, "y": 14, "x": 49, "z": 73}}