{"idx_to_token": {"1": " ", "2": "f", "3": "r", "4": "o", "5": "m", "6": "a", "7": "s", "8": "i", "9": "t", "10": "u", "11": "n", "12": "_", "13": "e", "14": "l", "15": "c", "16": "v", "17": "\n", "18": "p", "19": ",", "20": "d", "21": "I", "22": "y", "23": "h", "24": "b", "25": "q", "26": ".", "27": "T", "28": "k", "29": "g", "30": "D", "31": "1", "32": "8", "33": "6", "34": "W", "35": "w", "36": "S", "37": "-", "38": "j", "39": "x", "40": "?", "41": "A", "42": "]", "43": "\"", "44": "O", "45": "F", "46": "N", "47": "H", "48": "=", "49": "E", "50": "J", "51": "L", "52": "C", "53": "!", "54": "Y", "55": "'", "56": "0", "57": "B", "58": ";", "59": "P", "60": "G", "61": "5", "62": "3", "63": "7", "64": "9", "65": "4", "66": "R", "67": "U", "68": "M", "69": ")", "70": "#", "71": ":", "72": "V", "73": "z", "74": "2", "75": "K", "76": "(", "77": "X", "78": "*", "79": "\t"}, "token_to_idx": {"\t": 79, "\n": 17, "!": 53, " ": 1, "#": 70, "\"": 43, "'": 55, ")": 69, "(": 76, "*": 78, "-": 37, ",": 19, ".": 26, "1": 31, "0": 56, "3": 62, "2": 74, "5": 61, "4": 65, "7": 63, "6": 33, "9": 64, "8": 32, ";": 58, ":": 71, "=": 48, "?": 40, "A": 41, "C": 52, "B": 57, "E": 49, "D": 30, "G": 60, "F": 45, "I": 21, "H": 47, "K": 75, "J": 50, "M": 68, "L": 51, "O": 44, "N": 46, "P": 59, "S": 36, "R": 66, "U": 67, "T": 27, "W": 34, "V": 72, "Y": 54, "X": 77, "]": 42, "_": 12, "a": 6, "c": 15, "b": 24, "e": 13, "d": 20, "g": 29, "f": 2, "i": 8, "h": 23, "k": 28, "j": 38, "m": 5, "l": 14, "o": 4, "n": 11, "q": 25, "p": 18, "s": 7, "r": 3, "u": 10, "t": 9, "w": 35, "v": 16, "y": 22, "x": 39, "z": 73}}