{"idx_to_token": {"1": "i", "2": "n", "3": "g", "4": " ", "5": "y", "6": "o", "7": "u", "8": "t", "9": "a", "10": "e", "11": "d", "12": "p", "13": "l", "14": "c", "15": "f", "16": ",", "17": "r", "18": "h", "19": "w", "20": "s", "21": ".", "22": "H", "23": "m", "24": "v", "25": "k", "26": "\"", "27": "O", "28": "3", "29": "0", "30": "\n", "31": "A", "32": "b", "33": "'", "34": "_", "35": "F", "36": "P", "37": "j", "38": "4", "39": "6", "40": "C", "41": "-", "42": "I", "43": "!", "44": "B", "45": "M", "46": "S", "47": "x", "48": "T", "49": "W", "50": ";", "51": "=", "52": "?", "53": "#", "54": "N", "55": "R", "56": "E", "57": "q", "58": "1", "59": "8", "60": "L", "61": "K", "62": "J", "63": "X", "64": "U", "65": "9", "66": "2", "67": "V", "68": "D", "69": "z", "70": "G", "71": "Y", "72": "[", "73": "7", "74": "5", "75": ")", "76": "/", "77": "(", "78": "Z", "79": "\t"}, "token_to_idx": {"\t": 79, "\n": 30, "!": 43, " ": 4, "#": 53, "\"": 26, "'": 33, ")": 75, "(": 77, "-": 41, ",": 16, "/": 76, ".": 21, "1": 58, "0": 29, "3": 28, "2": 66, "5": 74, "4": 38, "7": 73, "6": 39, "9": 65, "8": 59, ";": 50, "=": 51, "?": 52, "A": 31, "C": 40, "B": 44, "E": 56, "D": 68, "G": 70, "F": 35, "I": 42, "H": 22, "K": 61, "J": 62, "M": 45, "L": 60, "O": 27, "N": 54, "P": 36, "S": 46, "R": 55, "U": 64, "T": 48, "W": 49, "V": 67, "Y": 71, "X": 63, "[": 72, "Z": 78, "_": 34, "a": 9, "c": 14, "b": 32, "e": 10, "d": 11, "g": 3, "f": 15, "i": 1, "h": 18, "k": 25, "j": 37, "m": 23, "l": 13, "o": 6, "n": 2, "q": 57, "p": 12, "s": 20, "r": 17, "u": 7, "t": 8, "w": 19, "v": 24, "y": 5, "x": 47, "z": 69}}