{"idx_to_token": {"1": "l", "2": "e", "3": "n", "4": "c", "5": "\n", "6": "o", "7": "f", "8": " ", "9": "t", "10": "u", "11": "m", "12": "r", "13": ",", "14": "p", "15": ";", "16": "M", "17": ".", "18": "s", "19": "i", "20": "h", "21": "a", "22": "y", "23": "w", "24": "d", "25": "b", "26": "P", "27": "'", "28": "A", "29": "v", "30": "g", "31": "x", "32": "\"", "33": "_", "34": "j", "35": "k", "36": "F", "37": "C", "38": "E", "39": "D", "40": "R", "41": "H", "42": "I", "43": "q", "44": ":", "45": "9", "46": "5", "47": "0", "48": "T", "49": "!", "50": "Y", "51": "G", "52": "-", "53": "W", "54": "S", "55": "O", "56": "z", "57": "U", "58": "B", "59": "=", "60": "6", "61": "N", "62": "3", "63": "K", "64": ")", "65": "L", "66": "2", "67": "4", "68": "V", "69": "?", "70": "1", "71": "J", "72": "*", "73": "8", "74": "(", "75": "7", "76": "]", "77": "[", "78": "#", "79": "Z", "80": "Q", "81": "\t"}, "token_to_idx": {"\t": 81, "\n": 5, "!": 49, " ": 8, "#": 78, "\"": 32, "'": 27, ")": 64, "(": 74, "*": 72, "-": 52, ",": 13, ".": 17, "1": 70, "0": 47, "3": 62, "2": 66, "5": 46, "4": 67, "7": 75, "6": 60, "9": 45, "8": 73, ";": 15, ":": 44, "=": 59, "?": 69, "A": 28, "C": 37, "B": 58, "E": 38, "D": 39, "G": 51, "F": 36, "I": 42, "H": 41, "K": 63, "J": 71, "M": 16, "L": 65, "O": 55, "N": 61, "Q": 80, "P": 26, "S": 54, "R": 40, "U": 57, "T": 48, "W": 53, "V": 68, "Y": 50, "[": 77, "Z": 79, "]": 76, "_": 33, "a": 21, "c": 4, "b": 25, "e": 2, "d": 24, "g": 30, "f": 7, "i": 19, "h": 20, "k": 35, "j": 34, "m": 11, "l": 1, "o": 6, "n": 3, "q": 43, "p": 14, "s": 18, "r": 12, "u": 10, "t": 9, "w": 23, "v": 29, "y": 22, "x": 31, "z": 56}}