{"idx_to_token": {"1": " ", "2": "a", "3": "r", "4": "t", "5": "i", "6": "c", "7": "l", "8": "e", "9": ",", "10": "o", "11": "n", "12": "y", "13": "w", "14": "h", "15": "g", "16": "u", "17": "p", "18": "f", "19": "d", "20": "s", "21": "v", "22": ".", "23": "I", "24": "M", "25": "-", "26": "b", "27": "T", "28": "m", "29": "\n", "30": "x", "31": "S", "32": "k", "33": "'", "34": "D", "35": "\"", "36": "?", "37": "H", "38": "!", "39": "q", "40": "P", "41": "J", "42": "F", "43": "V", "44": "R", "45": ")", "46": "G", "47": "z", "48": "A", "49": "C", "50": "N", "51": "W", "52": "Y", "53": ":", "54": "=", "55": "_", "56": "j", "57": "O", "58": "L", "59": "5", "60": "1", "61": "4", "62": "]", "63": "B", "64": "2", "65": "7", "66": "E", "67": "3", "68": "#", "69": "9", "70": "K", "71": ";", "72": "U", "73": "X", "74": "8", "75": "6", "76": "0", "77": "Q", "78": "[", "79": "\t"}, "token_to_idx": {"\t": 79, "\n": 29, "!": 38, " ": 1, "#": 68, "\"": 35, "'": 33, ")": 45, "-": 25, ",": 9, ".": 22, "1": 60, "0": 76, "3": 67, "2": 64, "5": 59, "4": 61, "7": 65, "6": 75, "9": 69, "8": 74, ";": 71, ":": 53, "=": 54, "?": 36, "A": 48, "C": 49, "B": 63, "E": 66, "D": 34, "G": 46, "F": 42, "I": 23, "H": 37, "K": 70, "J": 41, "M": 24, "L": 58, "O": 57, "N": 50, "Q": 77, "P": 40, "S": 31, "R": 44, "U": 72, "T": 27, "W": 51, "V": 43, "Y": 52, "X": 73, "[": 78, "]": 62, "_": 55, "a": 2, "c": 6, "b": 26, "e": 8, "d": 19, "g": 15, "f": 18, "i": 5, "h": 14, "k": 32, "j": 56, "m": 28, "l": 7, "o": 10, "n": 11, "q": 39, "p": 17, "s": 20, "r": 3, "u": 16, "t": 4, "w": 13, "v": 21, "y": 12, "x": 30, "z": 47}}