{"idx_to_token": {"1": "s", "2": "h", "3": " ", "4": "p", "5": "o", "6": "l", "7": "i", "8": "f", "9": "n", "10": ",", "11": "a", "12": "t", "13": "e", "14": "r", "15": "m", "16": "y", "17": "\n", "18": "c", "19": "g", "20": "C", "21": "d", "22": "j", "23": ".", "24": "T", "25": "b", "26": "v", "27": "(", "28": "F", "29": "E", "30": "H", "31": "P", "32": "!", "33": "5", "34": "M", "35": "u", "36": ";", "37": "3", "38": "4", "39": "L", "40": "I", "41": "w", "42": "k", "43": "W", "44": "1", "45": "7", "46": "S", "47": "_", "48": "2", "49": "9", "50": ")", "51": "x", "52": ":", "53": "\"", "54": "Y", "55": "R", "56": "q", "57": "'", "58": "A", "59": "0", "60": "8", "61": "-", "62": "=", "63": "O", "64": "N", "65": "V", "66": "D", "67": "]", "68": "U", "69": "K", "70": "B", "71": "?", "72": "$", "73": "G", "74": "6", "75": "z", "76": "#", "77": "X", "78": "J", "79": "[", "80": "Z", "81": "\t"}, "token_to_idx": {"\t": 81, "\n": 17, "!": 32, " ": 3, "#": 76, "\"": 53, "$": 72, "'": 57, ")": 50, "(": 27, "-": 61, ",": 10, ".": 23, "1": 44, "0": 59, "3": 37, "2": 48, "5": 33, "4": 38, "7": 45, "6": 74, "9": 49, "8": 60, ";": 36, ":": 52, "=": 62, "?": 71, "A": 58, "C": 20, "B": 70, "E": 29, "D": 66, "G": 73, "F": 28, "I": 40, "H": 30, "K": 69, "J": 78, "M": 34, "L": 39, "O": 63, "N": 64, "P": 31, "S": 46, "R": 55, "U": 68, "T": 24, "W": 43, "V": 65, "Y": 54, "X": 77, "[": 79, "Z": 80, "]": 67, "_": 47, "a": 11, "c": 18, "b": 25, "e": 13, "d": 21, "g": 19, "f": 8, "i": 7, "h": 2, "k": 42, "j": 22, "m": 15, "l": 6, "o": 5, "n": 9, "q": 56, "p": 4, "s": 1, "r": 14, "u": 35, "t": 12, "w": 41, "v": 26, "y": 16, "x": 51, "z": 75}}