{"idx_to_token": {"1": "t", "2": "h", "3": "a", "4": " ", "5": "w", "6": "i", "7": "r", "8": "e", "9": "\"", "10": "f", "11": "l", "12": ",", "13": "4", "14": "9", "15": "\n", "16": "N", "17": "y", "18": "-", "19": "I", "20": "n", "21": "c", "22": "u", "23": "d", "24": "'", "25": "s", "26": "m", "27": "p", "28": "b", "29": ".", "30": "S", "31": "o", "32": "A", "33": "K", "34": "q", "35": "T", "36": ":", "37": "k", "38": "g", "39": "v", "40": "P", "41": "C", "42": ";", "43": "x", "44": "G", "45": "_", "46": "6", "47": "1", "48": "5", "49": "2", "50": "O", "51": "F", "52": "8", "53": "3", "54": "0", "55": "E", "56": "M", "57": "W", "58": "H", "59": "j", "60": "7", "61": "!", "62": "D", "63": "J", "64": "[", "65": "#", "66": "V", "67": "z", "68": "(", "69": "?", "70": "L", "71": "Y", "72": "=", "73": "B", "74": ")", "75": "R", "76": "]", "77": "Z", "78": "U", "79": "\t"}, "token_to_idx": {"\t": 79, "\n": 15, "!": 61, " ": 4, "#": 65, "\"": 9, "'": 24, ")": 74, "(": 68, "-": 18, ",": 12, ".": 29, "1": 47, "0": 54, "3": 53, "2": 49, "5": 48, "4": 13, "7": 60, "6": 46, "9": 14, "8": 52, ";": 42, ":": 36, "=": 72, "?": 69, "A": 32, "C": 41, "B": 73, "E": 55, "D": 62, "G": 44, "F": 51, "I": 19, "H": 58, "K": 33, "J": 63, "M": 56, "L": 70, "O": 50, "N": 16, "P": 40, "S": 30, "R": 75, "U": 78, "T": 35, "W": 57, "V": 66, "Y": 71, "[": 64, "Z": 77, "]": 76, "_": 45, "a": 3, "c": 21, "b": 28, "e": 8, "d": 23, "g": 38, "f": 10, "i": 6, "h": 2, "k": 37, "j": 59, "m": 26, "l": 11, "o": 31, "n": 20, "q": 34, "p": 27, "s": 25, "r": 7, "u": 22, "t": 1, "w": 5, "v": 39, "y": 17, "x": 43, "z": 67}}