{"idx_to_token": {"1": "\n", "2": "I", "3": " ", "4": "c", "5": "o", "6": "m", "7": "a", "8": "s", "9": "'", "10": "h", "11": "w", "12": "e", "13": "t", "14": "r", "15": ",", "16": "y", "17": "n", "18": "f", "19": "g", "20": "d", "21": ";", "22": "T", "23": "b", "24": "l", "25": ".", "26": "L", "27": "i", "28": "v", "29": ":", "30": "A", "31": "!", "32": "k", "33": "p", "34": "C", "35": "E", "36": "B", "37": "S", "38": "F", "39": "O", "40": "R", "41": "D", "42": "N", "43": "u", "44": "J", "45": "-", "46": "?", "47": "W", "48": "M", "49": "K", "50": "G", "51": "H", "52": "U", "53": "j", "54": "Y", "55": "P", "56": "z", "57": "q", "58": "Q", "59": "Z", "60": "V", "61": "x", "62": "X", "63": "\t"}, "token_to_idx": {"\t": 63, "\n": 1, "!": 31, " ": 3, "'": 9, "-": 45, ",": 15, ".": 25, ";": 21, ":": 29, "?": 46, "A": 30, "C": 34, "B": 36, "E": 35, "D": 41, "G": 50, "F": 38, "I": 2, "H": 51, "K": 49, "J": 44, "M": 48, "L": 26, "O": 39, "N": 42, "Q": 58, "P": 55, "S": 37, "R": 40, "U": 52, "T": 22, "W": 47, "V": 60, "Y": 54, "X": 62, "Z": 59, "a": 7, "c": 4, "b": 23, "e": 12, "d": 20, "g": 19, "f": 18, "i": 27, "h": 10, "k": 32, "j": 53, "m": 6, "l": 24, "o": 5, "n": 17, "q": 57, "p": 33, "s": 8, "r": 14, "u": 43, "t": 13, "w": 11, "v": 28, "y": 16, "x": 61, "z": 56}}