{"idx_to_token": {"1": "h", "2": "e", "3": "n", "4": " ", "5": "s", "6": "t", "7": "o", "8": "u", "9": "g", "10": "d", "11": "i", "12": "f", "13": "r", "14": "a", "15": "c", "16": "v", "17": "l", "18": "w", "19": "b", "20": "k", "21": "p", "22": "\n", "23": "m", "24": ",", "25": "V", "26": ".", "27": "A", "28": "S", "29": "y", "30": "W", "31": "\"", "32": "I", "33": "3", "34": "7", "35": "J", "36": "4", "37": "0", "38": "x", "39": "?", "40": "6", "41": "P", "42": "1", "43": "2", "44": "#", "45": "F", "46": "D", "47": "!", "48": "j", "49": "-", "50": "G", "51": "N", "52": "R", "53": "'", "54": "T", "55": "O", "56": "q", "57": ")", "58": "U", "59": "B", "60": "E", "61": "]", "62": "M", "63": "H", "64": "L", "65": "_", "66": ";", "67": "8", "68": "C", "69": ":", "70": "5", "71": "K", "72": "z", "73": "$", "74": "=", "75": "9", "76": "(", "77": "Y", "78": "X", "79": "[", "80": "\t"}, "token_to_idx": {"\t": 80, "\n": 22, "!": 47, " ": 4, "#": 44, "\"": 31, "$": 73, "'": 53, ")": 57, "(": 76, "-": 49, ",": 24, ".": 26, "1": 42, "0": 37, "3": 33, "2": 43, "5": 70, "4": 36, "7": 34, "6": 40, "9": 75, "8": 67, ";": 66, ":": 69, "=": 74, "?": 39, "A": 27, "C": 68, "B": 59, "E": 60, "D": 46, "G": 50, "F": 45, "I": 32, "H": 63, "K": 71, "J": 35, "M": 62, "L": 64, "O": 55, "N": 51, "P": 41, "S": 28, "R": 52, "U": 58, "T": 54, "W": 30, "V": 25, "Y": 77, "X": 78, "[": 79, "]": 61, "_": 65, "a": 14, "c": 15, "b": 19, "e": 2, "d": 10, "g": 9, "f": 12, "i": 11, "h": 1, "k": 20, "j": 48, "m": 23, "l": 17, "o": 7, "n": 3, "q": 56, "p": 21, "s": 5, "r": 13, "u": 8, "t": 6, "w": 18, "v": 16, "y": 29, "x": 38, "z": 72}}