{"idx_to_token": {"1": "e", "2": "s", "3": ",", "4": " ", "5": "a", "6": "I", "7": "w", "8": "i", "9": "l", "10": "h", "11": "t", "12": "o", "13": "m", "14": "c", "15": "y", "16": "?", "17": "A", "18": "u", "19": "g", "20": "d", "21": "f", "22": "r", "23": ".", "24": "E", "25": "b", "26": "j", "27": "v", "28": "2", "29": "3", "30": "1", "31": "\n", "32": "R", "33": "n", "34": "\"", "35": "k", "36": "-", "37": "p", "38": "q", "39": "C", "40": "T", "41": "x", "42": "D", "43": "O", "44": "0", "45": "_", "46": "V", "47": "7", "48": "5", "49": "4", "50": "8", "51": "!", "52": "W", "53": "'", "54": "G", "55": "P", "56": "B", "57": "S", "58": "F", "59": "N", "60": "K", "61": ":", "62": ";", "63": "H", "64": "M", "65": "#", "66": ")", "67": "9", "68": "U", "69": "Y", "70": "[", "71": "z", "72": "6", "73": "=", "74": "L", "75": "]", "76": "J", "77": "/", "78": "(", "79": "*", "80": "\t"}, "token_to_idx": {"\t": 80, "\n": 31, "!": 51, " ": 4, "#": 65, "\"": 34, "'": 53, ")": 66, "(": 78, "*": 79, "-": 36, ",": 3, "/": 77, ".": 23, "1": 30, "0": 44, "3": 29, "2": 28, "5": 48, "4": 49, "7": 47, "6": 72, "9": 67, "8": 50, ";": 62, ":": 61, "=": 73, "?": 16, "A": 17, "C": 39, "B": 56, "E": 24, "D": 42, "G": 54, "F": 58, "I": 6, "H": 63, "K": 60, "J": 76, "M": 64, "L": 74, "O": 43, "N": 59, "P": 55, "S": 57, "R": 32, "U": 68, "T": 40, "W": 52, "V": 46, "Y": 69, "[": 70, "]": 75, "_": 45, "a": 5, "c": 14, "b": 25, "e": 1, "d": 20, "g": 19, "f": 21, "i": 8, "h": 10, "k": 35, "j": 26, "m": 13, "l": 9, "o": 12, "n": 33, "q": 38, "p": 37, "s": 2, "r": 22, "u": 18, "t": 11, "w": 7, "v": 27, "y": 15, "x": 41, "z": 71}}