{"idx_to_token": {"1": "s", "2": "c", "3": "h", "4": "a", "5": "r", "6": "g", "7": "e", "8": ",", "9": " ", "10": "t", "11": "o", "12": "w", "13": "d", "14": "\n", "15": "m", "16": "n", "17": "b", "18": "y", "19": "p", "20": "i", "21": "l", "22": "f", "23": "-", "24": "k", "25": "u", "26": "P", "27": ".", "28": "A", "29": "v", "30": "_", "31": "W", "32": "!", "33": "\"", "34": "'", "35": "F", "36": "C", "37": "N", "38": "Y", "39": "x", "40": "B", "41": "j", "42": "I", "43": "H", "44": ";", "45": "O", "46": "1", "47": "0", "48": "4", "49": "D", "50": "R", "51": "]", "52": "=", "53": "S", "54": "?", "55": "J", "56": "T", "57": "8", "58": "2", "59": "(", "60": ")", "61": "7", "62": "3", "63": "9", "64": "E", "65": "M", "66": "V", "67": "X", "68": "Q", "69": "q", "70": "6", "71": ":", "72": "G", "73": "5", "74": "z", "75": "K", "76": "Z", "77": "U", "78": "#", "79": "L", "80": "*", "81": "/", "82": "\t"}, "token_to_idx": {"\t": 82, "\n": 14, "!": 32, " ": 9, "#": 78, "\"": 33, "'": 34, ")": 60, "(": 59, "*": 80, "-": 23, ",": 8, "/": 81, ".": 27, "1": 46, "0": 47, "3": 62, "2": 58, "5": 73, "4": 48, "7": 61, "6": 70, "9": 63, "8": 57, ";": 44, ":": 71, "=": 52, "?": 54, "A": 28, "C": 36, "B": 40, "E": 64, "D": 49, "G": 72, "F": 35, "I": 42, "H": 43, "K": 75, "J": 55, "M": 65, "L": 79, "O": 45, "N": 37, "Q": 68, "P": 26, "S": 53, "R": 50, "U": 77, "T": 56, "W": 31, "V": 66, "Y": 38, "X": 67, "Z": 76, "]": 51, "_": 30, "a": 4, "c": 2, "b": 17, "e": 7, "d": 13, "g": 6, "f": 22, "i": 20, "h": 3, "k": 24, "j": 41, "m": 15, "l": 21, "o": 11, "n": 16, "q": 69, "p": 19, "s": 1, "r": 5, "u": 25, "t": 10, "w": 12, "v": 29, "y": 18, "x": 39, "z": 74}}