{"idx_to_token": {"1": "o", "2": "w", "3": " ", "4": "c", "5": "l", "6": "s", "7": "e", "8": "f", "9": "t", "10": "h", "11": "r", "12": "y", "13": "u", "14": ".", "15": "T", "16": "X", "17": "C", "18": "a", "19": "i", "20": "n", "21": "g", "22": "m", "23": "p", "24": ",", "25": "I", "26": "d", "27": "'", "28": "k", "29": "3", "30": "9", "31": "\n", "32": "P", "33": ";", "34": "W", "35": "A", "36": "S", "37": ":", "38": "?", "39": "b", "40": "\"", "41": "H", "42": "K", "43": "[", "44": "v", "45": "=", "46": "-", "47": "#", "48": "M", "49": "F", "50": "(", "51": "2", "52": "E", "53": "q", "54": "L", "55": "j", "56": "x", "57": "Y", "58": "B", "59": "!", "60": "R", "61": "1", "62": "z", "63": "4", "64": "8", "65": ")", "66": "6", "67": "5", "68": "0", "69": "D", "70": "V", "71": "G", "72": "U", "73": "_", "74": "Q", "75": "O", "76": "N", "77": "7", "78": "*", "79": "]", "80": "J", "81": "/", "82": "\t"}, "token_to_idx": {"\t": 82, "\n": 31, "!": 59, " ": 3, "#": 47, "\"": 40, "'": 27, ")": 65, "(": 50, "*": 78, "-": 46, ",": 24, "/": 81, ".": 14, "1": 61, "0": 68, "3": 29, "2": 51, "5": 67, "4": 63, "7": 77, "6": 66, "9": 30, "8": 64, ";": 33, ":": 37, "=": 45, "?": 38, "A": 35, "C": 17, "B": 58, "E": 52, "D": 69, "G": 71, "F": 49, "I": 25, "H": 41, "K": 42, "J": 80, "M": 48, "L": 54, "O": 75, "N": 76, "Q": 74, "P": 32, "S": 36, "R": 60, "U": 72, "T": 15, "W": 34, "V": 70, "Y": 57, "X": 16, "[": 43, "]": 79, "_": 73, "a": 18, "c": 4, "b": 39, "e": 7, "d": 26, "g": 21, "f": 8, "i": 19, "h": 10, "k": 28, "j": 55, "m": 22, "l": 5, "o": 1, "n": 20, "q": 53, "p": 23, "s": 6, "r": 11, "u": 13, "t": 9, "w": 2, "v": 44, "y": 12, "x": 56, "z": 62}}