{"idx_to_token": {"1": "t", "2": "a", "3": "e", "4": " ", "5": "n", "6": "d", "7": "s", "8": "p", "9": "h", "10": "o", "11": "l", "12": "\n", "13": "i", "14": ".", "15": "I", "16": "f", "17": "c", "18": "m", "19": "b", "20": "y", "21": "\"", "22": "G", "23": "u", "24": "!", "25": "N", "26": "-", "27": "_", "28": "W", "29": ",", "30": "r", "31": "w", "32": "g", "33": "k", "34": "L", "35": "v", "36": "J", "37": "D", "38": "x", "39": "q", "40": "A", "41": "j", "42": "T", "43": ";", "44": "#", "45": "M", "46": "R", "47": "F", "48": "z", "49": "5", "50": "1", "51": "7", "52": "2", "53": "3", "54": "B", "55": ":", "56": "8", "57": "P", "58": "=", "59": "H", "60": "Y", "61": "?", "62": "'", "63": "C", "64": "O", "65": "4", "66": "6", "67": "9", "68": ")", "69": "E", "70": "S", "71": "V", "72": "(", "73": "0", "74": "U", "75": "*", "76": "K", "77": "X", "78": "[", "79": "\t"}, "token_to_idx": {"\t": 79, "\n": 12, "!": 24, " ": 4, "#": 44, "\"": 21, "'": 62, ")": 68, "(": 72, "*": 75, "-": 26, ",": 29, ".": 14, "1": 50, "0": 73, "3": 53, "2": 52, "5": 49, "4": 65, "7": 51, "6": 66, "9": 67, "8": 56, ";": 43, ":": 55, "=": 58, "?": 61, "A": 40, "C": 63, "B": 54, "E": 69, "D": 37, "G": 22, "F": 47, "I": 15, "H": 59, "K": 76, "J": 36, "M": 45, "L": 34, "O": 64, "N": 25, "P": 57, "S": 70, "R": 46, "U": 74, "T": 42, "W": 28, "V": 71, "Y": 60, "X": 77, "[": 78, "_": 27, "a": 2, "c": 17, "b": 19, "e": 3, "d": 6, "g": 32, "f": 16, "i": 13, "h": 9, "k": 33, "j": 41, "m": 18, "l": 11, "o": 10, "n": 5, "q": 39, "p": 8, "s": 7, "r": 30, "u": 23, "t": 1, "w": 31, "v": 35, "y": 20, "x": 38, "z": 48}}