{"idx_to_token": {"1": "a", "2": "v", "3": "e", "4": "!", "5": "\r", "6": "\n", "7": "A", "8": "n", "9": "d", "10": " ", "11": "m", "12": "y", "13": "t", "14": "l", "15": "h", "16": "i", "17": ":", "18": "k", "19": "s", "20": ".", "21": "W", "22": "o", "23": "w", "24": "U", "25": "u", "26": "c", "27": "'", "28": "r", "29": ",", "30": "B", "31": "f", "32": ";", "33": "O", "34": "b", "35": "S", "36": "g", "37": "H", "38": "R", "39": "T", "40": "F", "41": "p", "42": "I", "43": "C", "44": "M", "45": "N", "46": "G", "47": "E", "48": "q", "49": "L", "50": "D", "51": "K", "52": "x", "53": "?", "54": "-", "55": "Y", "56": "P", "57": "X", "58": "Z", "59": "\t", "60": "\"", "61": "V", "62": "J", "63": "z", "64": "Q", "65": "j", "66": ")", "67": "3", "68": "2", "69": "0", "70": "(", "71": "1", "72": "5", "73": "7", "74": "4", "75": "6", "76": "8"}, "token_to_idx": {"\t": 59, "\n": 6, "\r": 5, "!": 4, " ": 10, "\"": 60, "'": 27, ")": 66, "(": 70, "-": 54, ",": 29, ".": 20, "1": 71, "0": 69, "3": 67, "2": 68, "5": 72, "4": 74, "7": 73, "6": 75, "8": 76, ";": 32, ":": 17, "?": 53, "A": 7, "C": 43, "B": 30, "E": 47, "D": 50, "G": 46, "F": 40, "I": 42, "H": 37, "K": 51, "J": 62, "M": 44, "L": 49, "O": 33, "N": 45, "Q": 64, "P": 56, "S": 35, "R": 38, "U": 24, "T": 39, "W": 21, "V": 61, "Y": 55, "X": 57, "Z": 58, "a": 1, "c": 26, "b": 34, "e": 3, "d": 9, "g": 36, "f": 31, "i": 16, "h": 15, "k": 18, "j": 65, "m": 11, "l": 14, "o": 22, "n": 8, "q": 48, "p": 41, "s": 19, "r": 28, "u": 25, "t": 13, "w": 23, "v": 2, "y": 12, "x": 52, "z": 63}}